deeppipe_api/__init__.py
deeppipe_api/deeppipe.py
deeppipe_api/modules.py
deeppipe_api/requirements.txt
deeppipe_api/utils.py
deeppipe_api/experiments/__init__.py
deeppipe_api/experiments/deep_pipe.py
deeppipe_api/experiments/meta_test.py
deeppipe_api/experiments/meta_train.py
deeppipe_api/experiments/modules.py
deeppipe_api/experiments/readme.md
deeppipe_api/experiments/requirements_all.txt
deeppipe_api/experiments/requirements_deep_pipe.txt
deeppipe_api/experiments/test_openml.py
deeppipe_api/experiments/utils.py
deeppipe_api/experiments/automl_baselines/autoprognosis_test.py
deeppipe_api/experiments/automl_baselines/oboe_bench_test.py
deeppipe_api/experiments/automl_baselines/pmf_bench_test.py
deeppipe_api/experiments/automl_baselines/rf_bench_test.py
deeppipe_api/experiments/automl_baselines/tpot_bench_test.py
deeppipe_api/experiments/baselines/__init__.py
deeppipe_api/experiments/baselines/baselines/bo.py
deeppipe_api/experiments/baselines/baselines/data_loader.py
deeppipe_api/experiments/baselines/baselines/rgpe.py
deeppipe_api/experiments/baselines/baselines/surrogates.py
deeppipe_api/experiments/baselines/baselines/test.py
deeppipe_api/experiments/baselines/fmlp/fmlp.py
deeppipe_api/experiments/baselines/fmlp/fmlp_loaders.py
deeppipe_api/experiments/baselines/fmlp/test_fmlp.py
deeppipe_api/experiments/baselines/fmlp/train_fmlp.py
deeppipe_api/experiments/baselines/oboe/__init__.py
deeppipe_api/experiments/baselines/oboe/convex_opt.py
deeppipe_api/experiments/baselines/oboe/linalg.py
deeppipe_api/experiments/baselines/oboe/model.py
deeppipe_api/experiments/baselines/oboe/pipeline.py
deeppipe_api/experiments/baselines/oboe/qr_computation.py
deeppipe_api/experiments/baselines/oboe/util.py
deeppipe_api/experiments/baselines/pmf/bo.py
deeppipe_api/experiments/baselines/pmf/gplvm.py
deeppipe_api/experiments/baselines/pmf/kernels.py
deeppipe_api/experiments/baselines/pmf/plotting.py
deeppipe_api/experiments/baselines/pmf/requirements.txt
deeppipe_api-0.1.4.dist-info/METADATA
deeppipe_api-0.1.4.dist-info/WHEEL
deeppipe_api-0.1.4.dist-info/licenses/LICENSE
deeppipe_api-0.1.4.dist-info/RECORD
